{"frames":{"pulsing-crimson-star0.png":{"frame":{"x":0,"y":0,"w":32,"h":32},"rotated":false,"trimmed":false,"spriteSourceSize":{"x":0,"y":0,"w":32,"h":32},"sourceSize":{"w":32,"h":32}},"pulsing-crimson-star1.png":{"frame":{"x":32,"y":0,"w":32,"h":32},"rotated":false,"trimmed":false,"spriteSourceSize":{"x":0,"y":0,"w":32,"h":32},"sourceSize":{"w":32,"h":32}},"pulsing-crimson-star2.png":{"frame":{"x":64,"y":0,"w":32,"h":32},"rotated":false,"trimmed":false,"spriteSourceSize":{"x":0,"y":0,"w":32,"h":32},"sourceSize":{"w":32,"h":32}},"pulsing-crimson-star3.png":{"frame":{"x":96,"y":0,"w":32,"h":32},"rotated":false,"trimmed":false,"spriteSourceSize":{"x":0,"y":0,"w":32,"h":32},"sourceSize":{"w":32,"h":32}},"pulsing-crimson-star4.png":{"frame":{"x":128,"y":0,"w":32,"h":32},"rotated":false,"trimmed":false,"spriteSourceSize":{"x":0,"y":0,"w":32,"h":32},"sourceSize":{"w":32,"h":32}},"pulsing-crimson-star5.png":{"frame":{"x":160,"y":0,"w":32,"h":32},"rotated":false,"trimmed":false,"spriteSourceSize":{"x":0,"y":0,"w":32,"h":32},"sourceSize":{"w":32,"h":32}},"pulsing-crimson-star6.png":{"frame":{"x":0,"y":32,"w":32,"h":32},"rotated":false,"trimmed":false,"spriteSourceSize":{"x":0,"y":0,"w":32,"h":32},"sourceSize":{"w":32,"h":32}},"pulsing-crimson-star7.png":{"frame":{"x":32,"y":32,"w":32,"h":32},"rotated":false,"trimmed":false,"spriteSourceSize":{"x":0,"y":0,"w":32,"h":32},"sourceSize":{"w":32,"h":32}},"pulsing-crimson-star8.png":{"frame":{"x":64,"y":32,"w":32,"h":32},"rotated":false,"trimmed":false,"spriteSourceSize":{"x":0,"y":0,"w":32,"h":32},"sourceSize":{"w":32,"h":32}},"pulsing-crimson-star9.png":{"frame":{"x":96,"y":32,"w":32,"h":32},"rotated":false,"trimmed":false,"spriteSourceSize":{"x":0,"y":0,"w":32,"h":32},"sourceSize":{"w":32,"h":32}},"pulsing-crimson-star10.png":{"frame":{"x":128,"y":32,"w":32,"h":32},"rotated":false,"trimmed":false,"spriteSourceSize":{"x":0,"y":0,"w":32,"h":32},"sourceSize":{"w":32,"h":32}},"pulsing-crimson-star11.png":{"frame":{"x":160,"y":32,"w":32,"h":32},"rotated":false,"trimmed":false,"spriteSourceSize":{"x":0,"y":0,"w":32,"h":32},"sourceSize":{"w":32,"h":32}},"pulsing-crimson-star12.png":{"frame":{"x":0,"y":64,"w":32,"h":32},"rotated":false,"trimmed":false,"spriteSourceSize":{"x":0,"y":0,"w":32,"h":32},"sourceSize":{"w":32,"h":32}},"pulsing-crimson-star13.png":{"frame":{"x":32,"y":64,"w":32,"h":32},"rotated":false,"trimmed":false,"spriteSourceSize":{"x":0,"y":0,"w":32,"h":32},"sourceSize":{"w":32,"h":32}},"pulsing-crimson-star14.png":{"frame":{"x":64,"y":64,"w":32,"h":32},"rotated":false,"trimmed":false,"spriteSourceSize":{"x":0,"y":0,"w":32,"h":32},"sourceSize":{"w":32,"h":32}},"pulsing-crimson-star15.png":{"frame":{"x":96,"y":64,"w":32,"h":32},"rotated":false,"trimmed":false,"spriteSourceSize":{"x":0,"y":0,"w":32,"h":32},"sourceSize":{"w":32,"h":32}},"pulsing-crimson-star16.png":{"frame":{"x":128,"y":64,"w":32,"h":32},"rotated":false,"trimmed":false,"spriteSourceSize":{"x":0,"y":0,"w":32,"h":32},"sourceSize":{"w":32,"h":32}},"pulsing-crimson-star17.png":{"frame":{"x":160,"y":64,"w":32,"h":32},"rotated":false,"trimmed":false,"spriteSourceSize":{"x":0,"y":0,"w":32,"h":32},"sourceSize":{"w":32,"h":32}},"pulsing-crimson-star18.png":{"frame":{"x":0,"y":96,"w":32,"h":32},"rotated":false,"trimmed":false,"spriteSourceSize":{"x":0,"y":0,"w":32,"h":32},"sourceSize":{"w":32,"h":32}},"pulsing-crimson-star19.png":{"frame":{"x":32,"y":96,"w":32,"h":32},"rotated":false,"trimmed":false,"spriteSourceSize":{"x":0,"y":0,"w":32,"h":32},"sourceSize":{"w":32,"h":32}},"pulsing-crimson-star20.png":{"frame":{"x":64,"y":96,"w":32,"h":32},"rotated":false,"trimmed":false,"spriteSourceSize":{"x":0,"y":0,"w":32,"h":32},"sourceSize":{"w":32,"h":32}},"pulsing-crimson-star21.png":{"frame":{"x":96,"y":96,"w":32,"h":32},"rotated":false,"trimmed":false,"spriteSourceSize":{"x":0,"y":0,"w":32,"h":32},"sourceSize":{"w":32,"h":32}},"pulsing-crimson-star22.png":{"frame":{"x":128,"y":96,"w":32,"h":32},"rotated":false,"trimmed":false,"spriteSourceSize":{"x":0,"y":0,"w":32,"h":32},"sourceSize":{"w":32,"h":32}},"pulsing-crimson-star23.png":{"frame":{"x":160,"y":96,"w":32,"h":32},"rotated":false,"trimmed":false,"spriteSourceSize":{"x":0,"y":0,"w":32,"h":32},"sourceSize":{"w":32,"h":32}},"pulsing-crimson-star24.png":{"frame":{"x":0,"y":128,"w":32,"h":32},"rotated":false,"trimmed":false,"spriteSourceSize":{"x":0,"y":0,"w":32,"h":32},"sourceSize":{"w":32,"h":32}},"pulsing-crimson-star25.png":{"frame":{"x":32,"y":128,"w":32,"h":32},"rotated":false,"trimmed":false,"spriteSourceSize":{"x":0,"y":0,"w":32,"h":32},"sourceSize":{"w":32,"h":32}},"pulsing-crimson-star26.png":{"frame":{"x":64,"y":128,"w":32,"h":32},"rotated":false,"trimmed":false,"spriteSourceSize":{"x":0,"y":0,"w":32,"h":32},"sourceSize":{"w":32,"h":32}},"pulsing-crimson-star27.png":{"frame":{"x":96,"y":128,"w":32,"h":32},"rotated":false,"trimmed":false,"spriteSourceSize":{"x":0,"y":0,"w":32,"h":32},"sourceSize":{"w":32,"h":32}},"pulsing-crimson-star28.png":{"frame":{"x":128,"y":128,"w":32,"h":32},"rotated":false,"trimmed":false,"spriteSourceSize":{"x":0,"y":0,"w":32,"h":32},"sourceSize":{"w":32,"h":32}},"pulsing-crimson-star29.png":{"frame":{"x":160,"y":128,"w":32,"h":32},"rotated":false,"trimmed":false,"spriteSourceSize":{"x":0,"y":0,"w":32,"h":32},"sourceSize":{"w":32,"h":32}},"pulsing-crimson-star30.png":{"frame":{"x":0,"y":160,"w":32,"h":32},"rotated":false,"trimmed":false,"spriteSourceSize":{"x":0,"y":0,"w":32,"h":32},"sourceSize":{"w":32,"h":32}},"pulsing-crimson-star31.png":{"frame":{"x":32,"y":160,"w":32,"h":32},"rotated":false,"trimmed":false,"spriteSourceSize":{"x":0,"y":0,"w":32,"h":32},"sourceSize":{"w":32,"h":32}}},"meta":{"app":"https://github.com/piskelapp/piskel/","version":"1.0","image":"pulsing-crimson-star.png","format":"RGBA8888","size":{"w":192,"h":192}}}