{"frames":{"pulsing-gray-star0.png":{"frame":{"x":0,"y":0,"w":32,"h":32},"rotated":false,"trimmed":false,"spriteSourceSize":{"x":0,"y":0,"w":32,"h":32},"sourceSize":{"w":32,"h":32}},"pulsing-gray-star1.png":{"frame":{"x":32,"y":0,"w":32,"h":32},"rotated":false,"trimmed":false,"spriteSourceSize":{"x":0,"y":0,"w":32,"h":32},"sourceSize":{"w":32,"h":32}},"pulsing-gray-star2.png":{"frame":{"x":64,"y":0,"w":32,"h":32},"rotated":false,"trimmed":false,"spriteSourceSize":{"x":0,"y":0,"w":32,"h":32},"sourceSize":{"w":32,"h":32}},"pulsing-gray-star3.png":{"frame":{"x":96,"y":0,"w":32,"h":32},"rotated":false,"trimmed":false,"spriteSourceSize":{"x":0,"y":0,"w":32,"h":32},"sourceSize":{"w":32,"h":32}},"pulsing-gray-star4.png":{"frame":{"x":128,"y":0,"w":32,"h":32},"rotated":false,"trimmed":false,"spriteSourceSize":{"x":0,"y":0,"w":32,"h":32},"sourceSize":{"w":32,"h":32}},"pulsing-gray-star5.png":{"frame":{"x":160,"y":0,"w":32,"h":32},"rotated":false,"trimmed":false,"spriteSourceSize":{"x":0,"y":0,"w":32,"h":32},"sourceSize":{"w":32,"h":32}},"pulsing-gray-star6.png":{"frame":{"x":0,"y":32,"w":32,"h":32},"rotated":false,"trimmed":false,"spriteSourceSize":{"x":0,"y":0,"w":32,"h":32},"sourceSize":{"w":32,"h":32}},"pulsing-gray-star7.png":{"frame":{"x":32,"y":32,"w":32,"h":32},"rotated":false,"trimmed":false,"spriteSourceSize":{"x":0,"y":0,"w":32,"h":32},"sourceSize":{"w":32,"h":32}},"pulsing-gray-star8.png":{"frame":{"x":64,"y":32,"w":32,"h":32},"rotated":false,"trimmed":false,"spriteSourceSize":{"x":0,"y":0,"w":32,"h":32},"sourceSize":{"w":32,"h":32}},"pulsing-gray-star9.png":{"frame":{"x":96,"y":32,"w":32,"h":32},"rotated":false,"trimmed":false,"spriteSourceSize":{"x":0,"y":0,"w":32,"h":32},"sourceSize":{"w":32,"h":32}},"pulsing-gray-star10.png":{"frame":{"x":128,"y":32,"w":32,"h":32},"rotated":false,"trimmed":false,"spriteSourceSize":{"x":0,"y":0,"w":32,"h":32},"sourceSize":{"w":32,"h":32}},"pulsing-gray-star11.png":{"frame":{"x":160,"y":32,"w":32,"h":32},"rotated":false,"trimmed":false,"spriteSourceSize":{"x":0,"y":0,"w":32,"h":32},"sourceSize":{"w":32,"h":32}},"pulsing-gray-star12.png":{"frame":{"x":0,"y":64,"w":32,"h":32},"rotated":false,"trimmed":false,"spriteSourceSize":{"x":0,"y":0,"w":32,"h":32},"sourceSize":{"w":32,"h":32}},"pulsing-gray-star13.png":{"frame":{"x":32,"y":64,"w":32,"h":32},"rotated":false,"trimmed":false,"spriteSourceSize":{"x":0,"y":0,"w":32,"h":32},"sourceSize":{"w":32,"h":32}},"pulsing-gray-star14.png":{"frame":{"x":64,"y":64,"w":32,"h":32},"rotated":false,"trimmed":false,"spriteSourceSize":{"x":0,"y":0,"w":32,"h":32},"sourceSize":{"w":32,"h":32}},"pulsing-gray-star15.png":{"frame":{"x":96,"y":64,"w":32,"h":32},"rotated":false,"trimmed":false,"spriteSourceSize":{"x":0,"y":0,"w":32,"h":32},"sourceSize":{"w":32,"h":32}},"pulsing-gray-star16.png":{"frame":{"x":128,"y":64,"w":32,"h":32},"rotated":false,"trimmed":false,"spriteSourceSize":{"x":0,"y":0,"w":32,"h":32},"sourceSize":{"w":32,"h":32}},"pulsing-gray-star17.png":{"frame":{"x":160,"y":64,"w":32,"h":32},"rotated":false,"trimmed":false,"spriteSourceSize":{"x":0,"y":0,"w":32,"h":32},"sourceSize":{"w":32,"h":32}},"pulsing-gray-star18.png":{"frame":{"x":0,"y":96,"w":32,"h":32},"rotated":false,"trimmed":false,"spriteSourceSize":{"x":0,"y":0,"w":32,"h":32},"sourceSize":{"w":32,"h":32}},"pulsing-gray-star19.png":{"frame":{"x":32,"y":96,"w":32,"h":32},"rotated":false,"trimmed":false,"spriteSourceSize":{"x":0,"y":0,"w":32,"h":32},"sourceSize":{"w":32,"h":32}},"pulsing-gray-star20.png":{"frame":{"x":64,"y":96,"w":32,"h":32},"rotated":false,"trimmed":false,"spriteSourceSize":{"x":0,"y":0,"w":32,"h":32},"sourceSize":{"w":32,"h":32}},"pulsing-gray-star21.png":{"frame":{"x":96,"y":96,"w":32,"h":32},"rotated":false,"trimmed":false,"spriteSourceSize":{"x":0,"y":0,"w":32,"h":32},"sourceSize":{"w":32,"h":32}},"pulsing-gray-star22.png":{"frame":{"x":128,"y":96,"w":32,"h":32},"rotated":false,"trimmed":false,"spriteSourceSize":{"x":0,"y":0,"w":32,"h":32},"sourceSize":{"w":32,"h":32}},"pulsing-gray-star23.png":{"frame":{"x":160,"y":96,"w":32,"h":32},"rotated":false,"trimmed":false,"spriteSourceSize":{"x":0,"y":0,"w":32,"h":32},"sourceSize":{"w":32,"h":32}},"pulsing-gray-star24.png":{"frame":{"x":0,"y":128,"w":32,"h":32},"rotated":false,"trimmed":false,"spriteSourceSize":{"x":0,"y":0,"w":32,"h":32},"sourceSize":{"w":32,"h":32}},"pulsing-gray-star25.png":{"frame":{"x":32,"y":128,"w":32,"h":32},"rotated":false,"trimmed":false,"spriteSourceSize":{"x":0,"y":0,"w":32,"h":32},"sourceSize":{"w":32,"h":32}},"pulsing-gray-star26.png":{"frame":{"x":64,"y":128,"w":32,"h":32},"rotated":false,"trimmed":false,"spriteSourceSize":{"x":0,"y":0,"w":32,"h":32},"sourceSize":{"w":32,"h":32}},"pulsing-gray-star27.png":{"frame":{"x":96,"y":128,"w":32,"h":32},"rotated":false,"trimmed":false,"spriteSourceSize":{"x":0,"y":0,"w":32,"h":32},"sourceSize":{"w":32,"h":32}},"pulsing-gray-star28.png":{"frame":{"x":128,"y":128,"w":32,"h":32},"rotated":false,"trimmed":false,"spriteSourceSize":{"x":0,"y":0,"w":32,"h":32},"sourceSize":{"w":32,"h":32}},"pulsing-gray-star29.png":{"frame":{"x":160,"y":128,"w":32,"h":32},"rotated":false,"trimmed":false,"spriteSourceSize":{"x":0,"y":0,"w":32,"h":32},"sourceSize":{"w":32,"h":32}},"pulsing-gray-star30.png":{"frame":{"x":0,"y":160,"w":32,"h":32},"rotated":false,"trimmed":false,"spriteSourceSize":{"x":0,"y":0,"w":32,"h":32},"sourceSize":{"w":32,"h":32}},"pulsing-gray-star31.png":{"frame":{"x":32,"y":160,"w":32,"h":32},"rotated":false,"trimmed":false,"spriteSourceSize":{"x":0,"y":0,"w":32,"h":32},"sourceSize":{"w":32,"h":32}}},"meta":{"app":"https://github.com/piskelapp/piskel/","version":"1.0","image":"pulsing-gray-star.png","format":"RGBA8888","size":{"w":192,"h":192}}}